{
  "chapter_id": "ch07",
  "chapter_title": "第6章 推理过程中有没有谬误",
  "word_count": 13428,
  "core_claims": [
    "评价论证时必须检查推理中的'谬误'(fallacies):带有欺骗性的推理手段,常通过错误假设、分散注意力或结论先行来糊弄读者。",
    "推理谬误主要有三种常见形式:提供需明显错误假设才能成立的推理;把无关信息伪装成相关来分散注意力;用结论本身作为证据的循环论证。",
    "不必死记硬背所有谬误名称,只要学会问关键问题(假设是否可疑、注意力是否被转移、结论是否在自证),就能识别大多数谬误。",
    "常见谬误包括:人身攻击、滑坡谬误、追求完美解决方案、偷换概念、诉诸公众、诉诸可疑权威、诉诸感情(含恶语中伤)、稻草人、虚假的两难选择、乱扣帽子(用命名代替解释)、光环效应、转移话题、循环论证。",
    "判断一个论证诉诸权威或诉诸公众是否为谬误,关键看该权威对论题是否有特别专门知识、该公众意见是否建立在充分研究之上——不应一概驳斥,而应小心评价。",
    "当论证里出现'不是…就是…''唯一的选择''两种选择分别是'等措辞时要警惕虚假两难;出现一个关键词在论证中重复出现时要警惕偷换概念;解决方案没消灭全部问题不代表方案不妥。",
    "在口头论辩里发现谬误后,建设性的做法是问对方有没有更好的理由来证实其结论,而不是立即终止对话。",
    "作者自己写作时应手边备一份谬误清单、细查自己的假设、具体阐述论题的利弊,才能避免自己构建论证大厦时落入陷阱。"
  ],
  "key_data": [
    {"value": "3 种形式", "context": "推理谬误的三种常见形式(错误假设 / 分散注意力 / 结论自证)"},
    {"value": "73%", "context": "作者举例中认为医用大麻应得到允许的民意调查比例(用以演示诉诸公众谬误)"},
    {"value": "13+ 种常见谬误", "context": "本章系统介绍的谬误:人身攻击、滑坡、追求完美解决方案、偷换概念、诉诸公众、诉诸可疑权威、诉诸感情、稻草人、虚假的两难选择、乱扣帽子、光环效应、转移话题、循环论证"}
  ],
  "key_terms": [
    "谬误(fallacy)",
    "人身攻击谬误(ad hominem fallacy)",
    "滑坡谬误(slippery slope fallacy)",
    "追求完美解决方案谬误(searching for perfect solutions)",
    "偷换概念谬误(equivocation fallacy)",
    "诉诸公众谬误(appeal to popularity / ad populum)",
    "诉诸可疑权威谬误(appeal to questionable authority)",
    "诉诸感情谬误(appeal to emotion)",
    "恶语中伤(name-calling)",
    "稻草人谬误(straw-person fallacy)",
    "虚假的两难选择谬误(either-or false dilemma)",
    "乱扣帽子谬误(explaining by naming)",
    "光环效应谬误(glittering generalities)",
    "转移话题谬误(red herring fallacy)",
    "循环论证谬误(begging the question)",
    "一厢情愿谬误(wishful thinking fallacy)"
  ],
  "author_examples": [
    "致编辑信:把参议员斯彭道贴标签为'自由派民主党人,动不动就提议增税'——人身攻击示例,回避增税是否合理的核心论题。",
    "桑迪 vs 朱莉谈女生联谊会:'你当然那样说,反正联谊会都不收你''你就是个输不起的人'——人身攻击对话示例。",
    "联邦通讯委员会禁酒类广告文章:两条理由——'会扩大到糖果、牛奶、鸡蛋等广告禁令'(滑坡)与'联邦政府行动不可能完全消除酒类消费'(追求完美解决方案)。",
    "家里添安保系统纯粹浪费钱'因为贼总有办法'——追求完美解决方案示例。",
    "医用大麻'社会共识'论证:'共识'在'科研人员共识'与'民意测验共识'之间偷换概念;并诉诸加州爱滋病协会这个可疑权威;最近调查 73% 为诉诸公众谬误。",
    "朗妲:柯蒂斯不是个男人(指胆小);艾伦:他二头肌那么发达(指体格)——偷换概念对话示例。",
    "政府儿童发展项目批评:'自以为是的鼓吹家''通用计划的试验品''将儿童从母亲身边夺走'——诉诸感情 + 恶语中伤;并把项目描绘成完全取代家庭,是稻草人。",
    "布兰妮·斯皮尔斯《马戏团》'世界上只有两种人——表演者与观看者'——虚假的两难选择对话例。",
    "市民:美国入侵伊拉克是错的;政客:你为什么恨美国——虚假的两难选择示例。",
    "大学室友丹问查克为什么行为古怪,凯文回答'他就是个混球'——乱扣帽子谬误示例。",
    "妈妈解释爸爸酗酒是'中年危机';心理学家解释朋友担心人说坏话是'妄想症'——乱扣帽子谬误示例。",
    "政治演说赞美古德哈特女士'民主''爱心''和平''繁荣''自由'——光环效应/美德词汇,分散听众对具体记录的注意力。",
    "医药公司修改止痛药研究数据:把议题(公众是否被误导)转到'还有成千上万人受益'——转移话题谬误。",
    "母女对话:妈妈问'为什么撒谎',女儿回'你总是挑我的错儿'——转移话题谬误。",
    "退学是不可取的,因为它是不好的——循环论证的简单示例。",
    "阅读传统教科书比电子文本学习效果好,因为以教材形式展现非常有利于学习——循环论证,理由只是重复结论。",
    "新闻来源保密两例对比:第(1)条提供了具体好处(增加举报概率),第(2)条只是重复'对集体有利',演示循环论证与合理论证的区别。",
    "练习第一篇:反对卫生局长的性教育建议——包含人身攻击、稻草人、一厢情愿、虚假的两难选择多种谬误。",
    "练习第二篇:反对禁养比特犬——包含人身攻击/恶语中伤、一厢情愿、追求完美解决方案、滑坡、诉诸公众多种谬误。",
    "练习第三篇:比尔 vs 泰勒关于窝藏恐怖分子国家的辩论——留作读者练习。"
  ],
  "structural_notes": "本章共 6 个小节,小节标题依次为:[不用死记硬背各种谬误的名称也能找到推理中的谬误, 有可能假设是明显错误的, 推理理由谬误百出(含练习一至练习二,介绍偷换概念/诉诸公众/诉诸可疑权威/诉诸感情/稻草人/虚假两难/乱扣帽子), 警惕分散注意力的干扰(含练习三练习四,介绍光环效应和转移话题), 愚弄人的循环论证, 使用这个关键问题 + 推理错误小汇总 + 扩展你关于谬误的知识 + 轮到你自己写时 + 来做做思维体操(含三篇练习)]。结构上按'三大类谬误机制'组织:第一类错误假设型(先以滑坡/追求完美 + 各种假设可疑的谬误,再扩展稻草人/虚假两难/乱扣帽子),第二类分散注意力型(光环效应 + 转移话题),第三类结论自证型(循环论证)。本章引入第五个关键问题'推理中有没有谬误'。"
}
